royal_sdk/__init__.py
royal_sdk/credential.py
royal_sdk/dynamic_folder.py
royal_sdk/folder.py
royal_sdk/task.py
royal_sdk/connections/__init__.py
royal_sdk/connections/file_transfer.py
royal_sdk/connections/terminal.py
royal_sdk-0.1.2.dist-info/METADATA
royal_sdk-0.1.2.dist-info/WHEEL
royal_sdk-0.1.2.dist-info/top_level.txt
royal_sdk-0.1.2.dist-info/RECORD
