Metadata-Version: 2.4
Name: royal-sdk
Version: 0.1.2
Summary: A Python SDK for Royal TSX/TS - create and manage connections, credentials, and folders programmatically
Author-email: N0P3 <n0p3.felix@gmail.com>
License: MIT
Project-URL: Changelog, https://github.com/B9O2/royal-sdk/blob/main/CHANGELOG.md
Keywords: royal,tsx,ts,sdk
Classifier: Development Status :: 4 - Beta
Classifier: Intended Audience :: Developers
Classifier: License :: OSI Approved :: MIT License
Classifier: Operating System :: OS Independent
Classifier: Programming Language :: Python :: 3
Classifier: Programming Language :: Python :: 3.8
Classifier: Programming Language :: Python :: 3.9
Classifier: Programming Language :: Python :: 3.10
Classifier: Programming Language :: Python :: 3.11
Classifier: Programming Language :: Python :: 3.12
Requires-Python: >=3.8
